sero/__init__.py
sero/prime_sero.py
sero/scale_sero.py
sero_ps-0.1.0.dist-info/LICENSE
sero_ps-0.1.0.dist-info/METADATA
sero_ps-0.1.0.dist-info/WHEEL
sero_ps-0.1.0.dist-info/top_level.txt
sero_ps-0.1.0.dist-info/RECORD
