Metadata-Version: 2.1
Name: sero-ps
Version: 0.1.0
Summary: A Python module for finding prime numbers using the Sieve of Eratosthenes
Author: Thirupathi
Author-email: suryathirupks@gmail.com
Classifier: Programming Language :: Python :: 3
Classifier: License :: OSI Approved :: MIT License
Classifier: Operating System :: OS Independent
Requires-Python: >=3.6
License-File: LICENSE
